daily_leet/__init__.py
daily_leet/__main__.py
daily_leet/constants.py
daily_leet/fetch_data.py
daily_leet/language_support/__init__.py
daily_leet/language_support/cpp.py
daily_leet/language_support/golang.py
daily_leet/language_support/python3.py
daily_leet/language_support/rust.py
daily_leet/language_support/types.py
daily_leet/language_support/utils.py
daily_leet/main.py
daily_leet/utils.py
daily_leet-0.2.7.dist-info/WHEEL
daily_leet-0.2.7.dist-info/entry_points.txt
daily_leet-0.2.7.dist-info/METADATA
daily_leet-0.2.7.dist-info/RECORD
